MANIFEST.in
README.md
setup.py
coverart/__init__.py
coverart/config.py
coverart/gui.py
coverart/sources.py
coverart/utils.py
coverart.egg-info/PKG-INFO
coverart.egg-info/SOURCES.txt
coverart.egg-info/dependency_links.txt
coverart.egg-info/entry_points.txt
coverart.egg-info/requires.txt
coverart.egg-info/top_level.txt
coverart/icons/no-cover.svg
coverart/sources/allcdcovers.py
coverart/sources/amazoncovers.py
coverart/sources/discogscovers.py
coverart/sources/lastfmcovers.py
coverart/sources/walmartcovers.py
coverart/sources/yahoocovers.py
coverart/ui/add_folder_dialog.ui
coverart/ui/add_folder_progress_dialog.ui
coverart/ui/confirm_dialog.ui
coverart/ui/covers_dialog.ui
coverart/ui/main.ui
coverart/ui/patterns_dialog.ui
coverart/ui/search_progress_dialog.ui
coverart/ui/sources_dialog.ui